mitm_channel_based/__init__.py
mitm_channel_based/all.py
mitm_channel_based/log_messages.py
mitm_channel_based/mitm_code.py
mitm_channel_based/packet_processing.py
mitm_channel_based/wpaspy.py
mitm_channel_based-0.0.5.dist-info/METADATA
mitm_channel_based-0.0.5.dist-info/RECORD
mitm_channel_based-0.0.5.dist-info/WHEEL
mitm_channel_based-0.0.5.dist-info/top_level.txt
