Metadata-Version: 2.1
Name: mitm-channel-based
Version: 0.0.5
Summary: This package enable to use the computer as a Rogue AP in a MitM Channel-Based attack
Home-page: https://github.com/lucascouto/mitm-channel-based-package
Author: Lucas Woody
Author-email: loc.unb@gmail.com
License: UNKNOWN
Platform: UNKNOWN
Classifier: Programming Language :: Python :: 2
Classifier: License :: OSI Approved :: MIT License
Classifier: Operating System :: OS Independent
Requires-Dist: scapy
